LICENSE
MANIFEST.in
README.rst
requirements.txt
run_tests.sh
setup.py
cloudmailin/__init__.py
cloudmailin/models.py
cloudmailin/tests.py
cloudmailin/views.py
cloudmailin/test/__init__.py
cloudmailin/test/settings.py
cloudmailin/test/urls.py
cloudmailin/test/mail/html.txt
cloudmailin/test/mail/message.txt
cloudmailin/test/mail/plain.txt
django_cloudmailin.egg-info/PKG-INFO
django_cloudmailin.egg-info/SOURCES.txt
django_cloudmailin.egg-info/dependency_links.txt
django_cloudmailin.egg-info/top_level.txt