Metadata-Version: 1.0
Name: django-cloudmailin
Version: 0.1.1
Summary: Client for CloudMailin incoming email service
Home-page: http://github.com/sunlightlabs/django-cloudmailin/
Author: Jeremy Carbaugh
Author-email: jcarbaugh@sunlightfoundation.com
License: BSD License
Platform: any
Classifier: Development Status :: 4 - Beta
Classifier: Intended Audience :: Developers
Classifier: License :: OSI Approved :: BSD License
Classifier: Natural Language :: English
Classifier: Operating System :: OS Independent
Classifier: Programming Language :: Python
Classifier: Environment :: Web Environment
